mcu/__init__.py
mcu/cell/__init__.py
mcu/cell/cell.py
mcu/cell/cell_io.py
mcu/cell/parameters.py
mcu/cell/spg_wrapper.py
mcu/cell/utils.py
mcu/cp2k/__init__.py
mcu/cp2k/cp2k.py
mcu/cp2k/cp2k_io.py
mcu/crystal/__init__.py
mcu/crystal/crystal.py
mcu/crystal/crystal_io.py
mcu/crystal/utils.py
mcu/elk/__init__.py
mcu/elk/elk.py
mcu/elk/elk_io.py
mcu/pscf/__init__.py
mcu/pscf/pscf.py
mcu/pscf/pscf_io.py
mcu/pscf/utils.py
mcu/qe/__init__.py
mcu/qe/qe.py
mcu/qe/qe_io.py
mcu/utils/__init__.py
mcu/utils/elastic2D.py
mcu/utils/grid.py
mcu/utils/misc.py
mcu/utils/plot.py
mcu/utils/str_format.py
mcu/vasp/__init__.py
mcu/vasp/const.py
mcu/vasp/locpot.py
mcu/vasp/parity.py
mcu/vasp/poscar.py
mcu/vasp/utils.py
mcu/vasp/vasp_io.py
mcu/vasp/vasprun.py
mcu/vasp/wavecar.py
mcu/wannier90/__init__.py
mcu/wannier90/pywannier90_vasp.py
mcu/wannier90/utils.py
mcu/wannier90/w90.py
mcu/wannier90/w90_io.py
mcu-1.0.1.dist-info/LICENSE
mcu-1.0.1.dist-info/METADATA
mcu-1.0.1.dist-info/WHEEL
mcu-1.0.1.dist-info/top_level.txt
mcu-1.0.1.dist-info/zip-safe
mcu-1.0.1.dist-info/RECORD
